sendfile/__main__.py
sendfile/client.py
sendfile/server.py
sendfile/utils.py
sendfile-0.1.2.dist-info/LICENSE
sendfile-0.1.2.dist-info/METADATA
sendfile-0.1.2.dist-info/WHEEL
sendfile-0.1.2.dist-info/entry_points.txt
sendfile-0.1.2.dist-info/top_level.txt
sendfile-0.1.2.dist-info/RECORD
