Metadata-Version: 2.1
Name: sendfile
Version: 0.1.2
Summary: send and recieve files across the local network
Author-email: sctech <gamerselimiko@gmail.com>
Project-URL: homepage, https://github.com/sctech-tr/sendfile
Classifier: Programming Language :: Python :: 3
Classifier: Programming Language :: Python :: 3.12
Classifier: Programming Language :: Python :: 3.9
Classifier: License :: OSI Approved :: GNU Affero General Public License v3 or later (AGPLv3+)
Classifier: Operating System :: OS Independent
Requires-Python: >=3.9
License-File: LICENSE
Requires-Dist: requests
